jsconfpy.py
jsconfpy-1.3.0.dist-info/WHEEL
jsconfpy-1.3.0.dist-info/METADATA
jsconfpy-1.3.0.dist-info/RECORD
