Metadata-Version: 2.1
Name: jsconfpy
Version: 1.3.0
Summary: json save config - это библиотека легкого задания конфигурационных файлов
Author: iHelper
Author-email: pettorr.lu@gmail.com
Requires-Python: >=3.8,<4.0
Classifier: Programming Language :: Python :: 3
Classifier: Programming Language :: Python :: 3.8
Classifier: Programming Language :: Python :: 3.9
